Metadata-Version: 2.1
Name: oneNeuron-pypi-BihanBanerjee
Version: 0.0.3
Summary: It is an implementation of a perceptron
Home-page: https://github.com/BihanBanerjee/oneNeuron_pypi
Author: BihanBanerjee
Author-email: banerjeebihan456@gmail.com
License: UNKNOWN
Project-URL: Bug Tracker, https://github.com/BihanBanerjee/oneNeuron_pypiissues
Platform: UNKNOWN
Classifier: Programming Language :: Python :: 3
Classifier: License :: OSI Approved :: MIT License
Classifier: Operating System :: OS Independent
Requires-Python: >=3.7
License-File: LICENSE
